{"flowContents":{"identifier":"d1db21c9-39ca-379a-8e6b-21f5eceb3728","instanceIdentifier":"776f03d7-019c-1000-835d-f633109236c8","name":"GetandPutFile","comments":"","position":{"x":8.0,"y":-608.0},"processGroups":[],"remoteProcessGroups":[],"processors":[{"identifier":"f87ebb25-5fdf-386c-bb8c-8b380441fca5","instanceIdentifier":"76f1e71d-019c-1000-ad1e-0f8878a77814","name":"Pick up files from source folder","comments":"","position":{"x":72.0,"y":-552.0},"type":"org.apache.nifi.processors.standard.GetFile","bundle":{"group":"org.apache.nifi","artifact":"nifi-standard-nar","version":"2.8.0"},"properties":{"Keep Source File":"false","Minimum File Age":"0 sec","Polling Interval":"30 sec","Input Directory":"/Users/eceakansel/apache_nifi/source","Maximum File Age":null,"Batch Size":"10","Maximum File Size":null,"Minimum File Size":"0 B","Ignore Hidden Files":"true","Recurse Subdirectories":"true","File Filter":"[^\\.].*","Path Filter":null},"propertyDescriptors":{"Keep Source File":{"name":"Keep Source File","displayName":"Keep Source File","identifiesControllerService":false,"sensitive":false,"dynamic":false},"Minimum File Age":{"name":"Minimum File Age","displayName":"Minimum File Age","identifiesControllerService":false,"sensitive":false,"dynamic":false},"Polling Interval":{"name":"Polling Interval","displayName":"Polling Interval","identifiesControllerService":false,"sensitive":false,"dynamic":false},"Input Directory":{"name":"Input Directory","displayName":"Input Directory","identifiesControllerService":false,"sensitive":false,"dynamic":false},"Maximum File Age":{"name":"Maximum File Age","displayName":"Maximum File Age","identifiesControllerService":false,"sensitive":false,"dynamic":false},"Batch Size":{"name":"Batch Size","displayName":"Batch Size","identifiesControllerService":false,"sensitive":false,"dynamic":false},"Maximum File Size":{"name":"Maximum File Size","displayName":"Maximum File Size","identifiesControllerService":false,"sensitive":false,"dynamic":false},"Minimum File Size":{"name":"Minimum File Size","displayName":"Minimum File Size","identifiesControllerService":false,"sensitive":false,"dynamic":false},"Ignore Hidden Files":{"name":"Ignore Hidden Files","displayName":"Ignore Hidden Files","identifiesControllerService":false,"sensitive":false,"dynamic":false},"Recurse Subdirectories":{"name":"Recurse Subdirectories","displayName":"Recurse Subdirectories","identifiesControllerService":false,"sensitive":false,"dynamic":false},"File Filter":{"name":"File Filter","displayName":"File Filter","identifiesControllerService":false,"sensitive":false,"dynamic":false},"Path Filter":{"name":"Path Filter","displayName":"Path Filter","identifiesControllerService":false,"sensitive":false,"dynamic":false}},"style":{"background-color":"#ffffff"},"schedulingPeriod":"0 sec","schedulingStrategy":"TIMER_DRIVEN","executionNode":"ALL","penaltyDuration":"30 sec","yieldDuration":"1 sec","bulletinLevel":"WARN","runDurationMillis":0,"concurrentlySchedulableTaskCount":1,"autoTerminatedRelationships":[],"scheduledState":"ENABLED","retryCount":10,"retriedRelationships":[],"backoffMechanism":"PENALIZE_FLOWFILE","maxBackoffPeriod":"10 mins","componentType":"PROCESSOR","groupIdentifier":"d1db21c9-39ca-379a-8e6b-21f5eceb3728"},{"identifier":"69a55602-9461-3aca-b291-2830596e739d","instanceIdentifier":"76f6a26d-019c-1000-2ad0-6d4ae1ad582c","name":"Place Flow file in target folder","comments":"","position":{"x":656.0,"y":-616.0},"type":"org.apache.nifi.processors.standard.PutFile","bundle":{"group":"org.apache.nifi","artifact":"nifi-standard-nar","version":"2.8.0"},"properties":{"Group":null,"Owner":null,"Create Missing Directories":"true","Permissions":null,"Maximum File Count":null,"Last Modified Time":null,"Directory":"/Users/eceakansel/apache_nifi/target","Conflict Resolution Strategy":"replace"},"propertyDescriptors":{"Group":{"name":"Group","displayName":"Group","identifiesControllerService":false,"sensitive":false,"dynamic":false},"Owner":{"name":"Owner","displayName":"Owner","identifiesControllerService":false,"sensitive":false,"dynamic":false},"Create Missing Directories":{"name":"Create Missing Directories","displayName":"Create Missing Directories","identifiesControllerService":false,"sensitive":false,"dynamic":false},"Permissions":{"name":"Permissions","displayName":"Permissions","identifiesControllerService":false,"sensitive":false,"dynamic":false},"Maximum File Count":{"name":"Maximum File Count","displayName":"Maximum File Count","identifiesControllerService":false,"sensitive":false,"dynamic":false},"Last Modified Time":{"name":"Last Modified Time","displayName":"Last Modified Time","identifiesControllerService":false,"sensitive":false,"dynamic":false},"Directory":{"name":"Directory","displayName":"Directory","identifiesControllerService":false,"sensitive":false,"dynamic":false},"Conflict Resolution Strategy":{"name":"Conflict Resolution Strategy","displayName":"Conflict Resolution Strategy","identifiesControllerService":false,"sensitive":false,"dynamic":false}},"style":{},"schedulingPeriod":"0 sec","schedulingStrategy":"TIMER_DRIVEN","executionNode":"ALL","penaltyDuration":"30 sec","yieldDuration":"1 sec","bulletinLevel":"WARN","runDurationMillis":0,"concurrentlySchedulableTaskCount":1,"autoTerminatedRelationships":["success","failure"],"scheduledState":"ENABLED","retryCount":10,"retriedRelationships":[],"backoffMechanism":"PENALIZE_FLOWFILE","maxBackoffPeriod":"10 mins","componentType":"PROCESSOR","groupIdentifier":"d1db21c9-39ca-379a-8e6b-21f5eceb3728"}],"inputPorts":[],"outputPorts":[],"connections":[{"identifier":"181c7e9c-e7e4-3237-90c7-9abe78f5385a","instanceIdentifier":"76fa1641-019c-1000-8cfe-0ab9b53cff3d","name":"","source":{"id":"f87ebb25-5fdf-386c-bb8c-8b380441fca5","type":"PROCESSOR","groupId":"d1db21c9-39ca-379a-8e6b-21f5eceb3728","name":"Pick up files from source folder","comments":"","instanceIdentifier":"76f1e71d-019c-1000-ad1e-0f8878a77814"},"destination":{"id":"69a55602-9461-3aca-b291-2830596e739d","type":"PROCESSOR","groupId":"d1db21c9-39ca-379a-8e6b-21f5eceb3728","name":"Place Flow file in target folder","comments":"","instanceIdentifier":"76f6a26d-019c-1000-2ad0-6d4ae1ad582c"},"labelIndex":0,"zIndex":1,"selectedRelationships":["success"],"backPressureObjectThreshold":10000,"backPressureDataSizeThreshold":"1 GB","flowFileExpiration":"0 sec","prioritizers":[],"bends":[],"loadBalanceStrategy":"DO_NOT_LOAD_BALANCE","partitioningAttribute":"","loadBalanceCompression":"DO_NOT_COMPRESS","componentType":"CONNECTION","groupIdentifier":"d1db21c9-39ca-379a-8e6b-21f5eceb3728"}],"labels":[],"funnels":[],"controllerServices":[],"defaultFlowFileExpiration":"0 sec","defaultBackPressureObjectThreshold":10000,"defaultBackPressureDataSizeThreshold":"1 GB","scheduledState":"ENABLED","executionEngine":"INHERITED","maxConcurrentTasks":1,"statelessFlowTimeout":"1 min","componentType":"PROCESS_GROUP","flowFileConcurrency":"UNBOUNDED","flowFileOutboundPolicy":"STREAM_WHEN_AVAILABLE"},"externalControllerServices":{},"parameterContexts":{},"flowEncodingVersion":"1.0","parameterProviders":{},"latest":false}